huangyuanqi_fc_bigdata.py
huangyuanqi_fc_bigdata-2.0.dist-info/METADATA
huangyuanqi_fc_bigdata-2.0.dist-info/WHEEL
huangyuanqi_fc_bigdata-2.0.dist-info/top_level.txt
huangyuanqi_fc_bigdata-2.0.dist-info/RECORD
