Metadata-Version: 2.1
Name: huangyuanqi-fc-bigdata
Version: 2.0
Summary: 大数据三班
Home-page: UNKNOWN
Author: 大数据三班
Author-email: 2488084249@qq.com
License: UNKNOWN
Platform: UNKNOWN
